synodic_client/__init__.py
synodic_client/client.py
synodic_client/py.typed
synodic_client-0.1.1.dev2.dist-info/WHEEL
synodic_client-0.1.1.dev2.dist-info/METADATA
synodic_client-0.1.1.dev2.dist-info/licenses/LICENSE.md
synodic_client-0.1.1.dev2.dist-info/RECORD
