Metadata-Version: 2.1
Name: synodic_client
Version: 0.1.1.dev2
License: MIT
Author-email: Synodic Software <contact@synodic.software>
Requires-Python: >=3.11,<3.12
Requires-Dist: porringer>=0.0.0
Requires-Dist: pyside6>=5.1
Project-URL: homepage, https://github.com/Synodic-Software/Synodic-Client
Project-URL: repository, https://github.com/Synodic-Software/Synodic-Client
